drf_helpers/__init__.py
drf_helpers/action_maps.py
drf_helpers/filters.py
drf_helpers/metadata.py
drf_helpers/mixins.py
drf_helpers/negotiators.py
drf_helpers/pagination.py
drf_helpers/permissions.py
drf_helpers/routers.py
drf_helpers/routes.py
drf_helpers/serializers.py
drf_helpers/urls.py
drf_helpers/views.py
drf_helpers/viewsets.py
drf_helpers-0.1.7.dist-info/METADATA
drf_helpers-0.1.7.dist-info/RECORD
drf_helpers-0.1.7.dist-info/WHEEL
drf_helpers-0.1.7.dist-info/top_level.txt
